jenkinscfg/__init__.py
jenkinscfg/cli.py
jenkinscfg-0.1.0.dist-info/LICENSE
jenkinscfg-0.1.0.dist-info/METADATA
jenkinscfg-0.1.0.dist-info/WHEEL
jenkinscfg-0.1.0.dist-info/entry_points.txt
jenkinscfg-0.1.0.dist-info/top_level.txt
jenkinscfg-0.1.0.dist-info/RECORD
